{
  "stac_version": "1.0.0",
  "stac_extensions": [
    "https://stac-extensions.github.io/storage/v1.0.0/schema.json"
  ],
  "id": "20190822T183518Z_746_POM1_ST2_P",
  "collection": "NSL_SCENE",
  "type": "Feature",
  "bbox": [
    -97.7466867683867,
    30.278398961994966,
    -97.72990596574927,
    30.288621181865743
  ],
  "geometry": {
    "type": "Polygon",
    "coordinates": [
      [
        [
          -97.7466867683867,
          30.28754662370266
        ],
        [
          -97.74555747279238,
          30.278398961994966
        ],
        [
          -97.72990596574927,
          30.27972380176124
        ],
        [
          -97.73085242627444,
          30.288621181865743
        ],
        [
          -97.7466867683867,
          30.28754662370266
        ]
      ]
    ]
  },
  "properties": {
    "datetime": "2019-08-22T18:35:18+00:00",
    "mission": "SWIFT",
    "platform": "SWIFT_2",
    "instrument": "POM_1",
    "gsd": 0.20000000298023224
  },
  "assets": {
    "GEOTIFF_RGB_GCP": {
      "href": "gs://swiftera-processed-data/20190822T162258Z_TRAVIS_COUNTY/Published/REGION_0/20190822T183518Z_746_POM1_ST2_P.tif",
      "type": "image/vnd.stac.geotiff",
      "storage:platform": "GCP",
      "storage:region": "us-central1",
      "storage:requester_pays": true,
      "storage:tier": "Standard"
    },
    "THUMBNAIL_RGB_GCP": {
      "href": "gs://swiftera-processed-data/20190822T162258Z_TRAVIS_COUNTY/Published/REGION_0/20190822T183518Z_746_POM1_ST2_P.png",
      "type": "image/png",
      "storage:platform": "GCP",
      "storage:region": "us-central1",
      "storage:requester_pays": true,
      "storage:tier": "Standard"
    },
    "GEOTIFF_RGB_AWS": {
      "href": "s3://nsl-data-archive/20190822T162258Z_TRAVIS_COUNTY/Published/REGION_0/20190822T183518Z_746_POM1_ST2_P.tif",
      "type": "image/vnd.stac.geotiff",
      "storage:platform": "AWS",
      "storage:region": "us-central-1",
      "storage:requester_pays": true,
      "storage:tier": "Glacier"
    },
    "THUMBNAIL_RGB_AWS": {
      "href": "s3://nsl-data-archive/20190822T162258Z_TRAVIS_COUNTY/Published/REGION_0/20190822T183518Z_746_POM1_ST2_P.png",
      "type": "image/png",
      "storage:platform": "AWS",
      "storage:region": "us-central-1",
      "storage:requester_pays": true,
      "storage:tier": "Standard"
    }
  },
  "links": [
    {
      "href": "https://example.com/examples/item.json",
      "rel": "self"
    },
    {
      "href": "https://example.com/examples/item.json",
      "rel": "collection"
    }
  ]
}